artssat/__init__.py
artssat/arts_object.py
artssat/data_provider.py
artssat/dimensions.py
artssat/io.py
artssat/jacobian.py
artssat/models.py
artssat/simulation.py
artssat/atmosphere/__init__.py
artssat/atmosphere/atmosphere.py
artssat/atmosphere/atmospheric_quantity.py
artssat/atmosphere/catalogs.py
artssat/atmosphere/cloud_box.py
artssat/atmosphere/absorption/__init__.py
artssat/atmosphere/surface/__init__.py
artssat/atmosphere/surface/surface.py
artssat/dashboard/__init__.py
artssat/data/__init__.py
artssat/data/atmosphere.py
artssat/retrieval/__init__.py
artssat/retrieval/a_priori.py
artssat/scattering/__init__.py
artssat/scattering/scattering_species.py
artssat/scattering/solvers.py
artssat/scattering/ssdb.py
artssat/scattering/psd/__init__.py
artssat/scattering/psd/ab12.py
artssat/scattering/psd/binned.py
artssat/scattering/psd/d14.py
artssat/scattering/psd/fixed_shape.py
artssat/scattering/psd/modified_gamma.py
artssat/scattering/psd/my05.py
artssat/scattering/psd/arts/__init__.py
artssat/scattering/psd/arts/arts_psd.py
artssat/scattering/psd/data/__init__.py
artssat/scattering/psd/data/psd_data.py
artssat/sensor/__init__.py
artssat/sensor/sensor.py
artssat/sensor/utils.py
examples/data_provider/__init__.py
artssat-0.0.1.dist-info/LICENSE
artssat-0.0.1.dist-info/METADATA
artssat-0.0.1.dist-info/WHEEL
artssat-0.0.1.dist-info/top_level.txt
artssat-0.0.1.dist-info/RECORD
