Metadata-Version: 2.1
Name: artssat
Version: 0.0.1
Summary: High-level simulation and retrieval framework for microwave and IR remote sensing.
Home-page: https://github.com/simonpf/artssat
Author: Simon Pfreundschuh
Author-email: simon.pfreundschuh@chalmers.se
License: UNKNOWN
Project-URL: Source, https://github.com/simonpf/artssat/
Platform: UNKNOWN
Requires-Python: >=3.6
Requires-Dist: pyarts
Requires-Dist: typhon
Requires-Dist: netCDF4
